clikit/__init__.py
clikit/adapter/__init__.py
clikit/adapter/style_converter.py
clikit/api/__init__.py
clikit/api/application/__init__.py
clikit/api/application/application.py
clikit/api/args/__init__.py
clikit/api/args/args.py
clikit/api/args/args_parser.py
clikit/api/args/exceptions.py
clikit/api/args/format/__init__.py
clikit/api/args/format/abstract_option.py
clikit/api/args/format/args_format.py
clikit/api/args/format/args_format_builder.py
clikit/api/args/format/argument.py
clikit/api/args/format/command_name.py
clikit/api/args/format/command_option.py
clikit/api/args/format/option.py
clikit/api/args/raw_args.py
clikit/api/command/__init__.py
clikit/api/command/command.py
clikit/api/command/command_collection.py
clikit/api/command/exceptions.py
clikit/api/config/__init__.py
clikit/api/config/application_config.py
clikit/api/config/command_config.py
clikit/api/config/config.py
clikit/api/event/__init__.py
clikit/api/event/config_event.py
clikit/api/event/console_events.py
clikit/api/event/event.py
clikit/api/event/event_dispatcher.py
clikit/api/event/pre_handle_event.py
clikit/api/event/pre_resolve_event.py
clikit/api/exceptions.py
clikit/api/formatter/__init__.py
clikit/api/formatter/formatter.py
clikit/api/formatter/style.py
clikit/api/formatter/style_set.py
clikit/api/io/__init__.py
clikit/api/io/flags.py
clikit/api/io/input.py
clikit/api/io/input_stream.py
clikit/api/io/io.py
clikit/api/io/io_exception.py
clikit/api/io/output.py
clikit/api/io/output_stream.py
clikit/api/io/section_output.py
clikit/api/resolver/__init__.py
clikit/api/resolver/command_resolver.py
clikit/api/resolver/exceptions.py
clikit/api/resolver/resolved_command.py
clikit/args/__init__.py
clikit/args/argv_args.py
clikit/args/default_args_parser.py
clikit/args/inputs/__init__.py
clikit/args/string_args.py
clikit/args/token_parser.py
clikit/config/__init__.py
clikit/config/default_application_config.py
clikit/console_application.py
clikit/formatter/__init__.py
clikit-0.6.1.dist-info/LICENSE
clikit-0.6.1.dist-info/WHEEL
clikit-0.6.1.dist-info/METADATA
clikit-0.6.1.dist-info/RECORD
